{
  "id": "2025-06-19",
  "date": "2025-06-19",
  "title": "Game News Round-Up",
  "status": "published",
  "published_at": "2025-06-19T08:49:22.448+01:00",
  "updated_at": null,
  "summary": "Daily curated games-industry news digest for 19 June 2025.",
  "video": {
    "status": "none",
    "url": null,
    "embed_url": null,
    "platform": null,
    "duration_seconds": null
  },
  "sections": [
    {
      "id": "main_news",
      "label": "Game News Round-Up",
      "items": [
        {
          "id": "hades-2-gets-fresh-early-access-update-as-development-finall",
          "title": "**Hades 2 **gets fresh early access update as development finally approaches full release",
          "body": null,
          "url": "https://www.eurogamer.net/hades-2-gets-fresh-early-access-update-as-development-finally-approaches-full-release",
          "source": {
            "name": "Eurogamer",
            "domain": "eurogamer.net"
          },
          "metadata": {
            "story_type": "confirmed",
            "importance": "normal"
          }
        },
        {
          "id": "support-for-beat-saber-on-ps4-and-ps5-ends-shining-a-light-o",
          "title": "Support for **Beat Saber** on PS4 and PS5 ends, shining a light on PSVR2's lack of success",
          "body": null,
          "url": "https://www.eurogamer.net/support-for-beat-saber-on-ps4-and-ps4-ends-shining-a-light-on-psvr2s-lack-of-success",
          "source": {
            "name": "Eurogamer",
            "domain": "eurogamer.net"
          },
          "metadata": {
            "story_type": "confirmed",
            "importance": "normal"
          }
        },
        {
          "id": "nintendo-reveals-new-donkey-kong-bananza-gameplay-info-inclu",
          "title": "Nintendo reveals new **Donkey Kong Bananza** gameplay info, including Pauline reveal",
          "body": null,
          "url": "https://www.videogameschronicle.com/news/nintendo-reveals-new-donkey-kong-bananza-gameplay-info-including-pauline-reveal/",
          "source": {
            "name": "VGC",
            "domain": "videogameschronicle.com"
          },
          "metadata": {
            "story_type": "confirmed",
            "importance": "normal"
          }
        },
        {
          "id": "death-stranding-animated-film-confirmed-original-story-in-th",
          "title": "**Death Stranding animated film** confirmed: Original story in the works from Raised by Wolves writer",
          "body": null,
          "url": "https://www.videogameschronicle.com/news/death-stranding-animated-film-confirmed-original-story-in-the-works-from-raised-by-wolves-writer/",
          "source": {
            "name": "VGC",
            "domain": "videogameschronicle.com"
          },
          "metadata": {
            "story_type": "confirmed",
            "importance": "normal"
          }
        },
        {
          "id": "christophe-gans-silent-hill-2-movie-adaptation-gets-a-releas",
          "title": "Christophe Gans' **Silent Hill 2 movie adaptation** gets a release date - 23rd January 2026",
          "body": null,
          "url": "https://www.eurogamer.net/christophe-gans-faithful-silent-hill-2-movie-adaptation-gets-a-2026-release-date",
          "source": {
            "name": "Eurogamer",
            "domain": "eurogamer.net"
          },
          "metadata": {
            "story_type": "confirmed",
            "importance": "normal"
          }
        },
        {
          "id": "skate-reboot-just-months-away-from-launch-as-playtests-open",
          "title": "**Skate **reboot \"just months away\" from launch, as playtests open up to all who register before end of June",
          "body": null,
          "url": "https://www.eurogamer.net/skate-reboot-just-months-away-from-launch-as-playtests-open-up-to-all-who-register-before-end-of-june",
          "source": {
            "name": "Eurogamer",
            "domain": "eurogamer.net"
          },
          "metadata": {
            "story_type": "confirmed",
            "importance": "normal"
          }
        }
      ]
    },
    {
      "id": "free_games_subscription",
      "label": "Free Games / Subscription",
      "items": [
        {
          "id": "sega-games-for-ios-and-android-made-free-before-being-delist",
          "title": "**Sega games for iOS and Android **made free before being delisted",
          "body": null,
          "url": "https://www.videogameschronicle.com/news/sega-has-made-nine-of-its-mobile-retro-re-releases-free-before-theyre-delisted/",
          "source": {
            "name": "VGC",
            "domain": "videogameschronicle.com"
          },
          "metadata": {
            "story_type": "confirmed",
            "importance": "normal"
          },
          "bullets": [
            "Crazy Taxi Classic",
            "Golden Axe Classics",
            "Shining Force Classics",
            "Sonic CD Classic",
            "Sonic the Hedgehog 4 Episode II",
            "Streets of Rage Classic",
            "Streets of Rage 2 Classic",
            "Super Monkey Ball: Sakura",
            "Virtua Tennis Challenge"
          ]
        }
      ]
    },
    {
      "id": "business",
      "label": "Business",
      "items": [
        {
          "id": "warner-bros-games-promotes-three-studio-heads-as-it-focuses",
          "title": "**Warner Bros. Games** promotes three studio heads as it focuses on four key properties - Harry Potter, Mortal Kombat, DC Comics, and Game of Thrones",
          "body": null,
          "url": "https://www.gamesindustry.biz/warner-bros-games-promotes-three-studio-heads-as-it-focuses-on-four-key-properties",
          "source": {
            "name": "GamesIndustry.biz",
            "domain": "gamesindustry.biz"
          },
          "metadata": {
            "story_type": "confirmed",
            "importance": "normal"
          }
        },
        {
          "id": "developers-at-ubisoft-halifax-have-filed-to-unionise",
          "title": "Developers at **Ubisoft Halifax** have filed to unionise",
          "body": null,
          "url": "https://www.gamesindustry.biz/developers-at-ubisoft-halifax-have-filed-to-unionise",
          "source": {
            "name": "GamesIndustry.biz",
            "domain": "gamesindustry.biz"
          },
          "metadata": {
            "story_type": "confirmed",
            "importance": "normal"
          }
        },
        {
          "id": "aggro-crab-and-landfall-side-hustle-peak-has-sold-100-000-co",
          "title": "Aggro Crab and Landfall 'side hustle' **Peak **has sold 100,000 copies in 24 hours",
          "body": null,
          "url": "https://www.gamedeveloper.com/business/aggro-crab-side-hustle-peak-has-sold-100-000-copies-in-24-hours",
          "source": {
            "name": "Game Developer",
            "domain": "gamedeveloper.com"
          },
          "metadata": {
            "story_type": "confirmed",
            "importance": "normal"
          }
        },
        {
          "id": "a-roblox-game-about-growing-vegetables-is-seemingly-now-bigg",
          "title": "A **Roblox **game about growing vegetables is seemingly now bigger than Fortnite - 16m concurrent users",
          "body": null,
          "url": "https://www.eurogamer.net/a-roblox-game-about-growing-vegetables-is-seemingly-now-bigger-than-fortnite",
          "source": {
            "name": "Eurogamer",
            "domain": "eurogamer.net"
          },
          "metadata": {
            "story_type": "confirmed",
            "importance": "normal"
          },
          "bullets": [
            "Editor note: for context, PUBG holds the Steam record for most concurrent players... at 3.3m."
          ]
        }
      ]
    },
    {
      "id": "rumours",
      "label": "Rumours",
      "items": [
        {
          "id": "ps5-s-stellar-blade-is-reportedly-coming-to-nintendo-switch",
          "title": "PS5’s **Stellar Blade** is reportedly coming to Nintendo Switch 2",
          "body": null,
          "url": "https://www.videogameschronicle.com/news/ps5s-stellar-blade-is-reportedly-coming-to-nintendo-switch-2/",
          "source": {
            "name": "VGC",
            "domain": "videogameschronicle.com"
          },
          "metadata": {
            "story_type": "rumour",
            "rumour_status": "rumour",
            "importance": "normal"
          }
        },
        {
          "id": "tencent-says-report-about-acquisition-interest-in-nexon-is-u",
          "title": "**Tencent **says report about acquisition interest in Nexon is untrue",
          "body": null,
          "url": "https://www.gamesindustry.biz/nexon-reportedly-considering-acquisition-bid-from-tencent",
          "source": {
            "name": "GamesIndustry.biz",
            "domain": "gamesindustry.biz"
          },
          "metadata": {
            "story_type": "rumour",
            "rumour_status": "rumour",
            "importance": "normal"
          }
        },
        {
          "id": "microsoft-cutting-thousands-more-jobs-after-just-laying-off",
          "title": "**Microsoft **cutting ‘thousands more jobs’ after just laying off 6,000 people",
          "body": null,
          "url": "https://insider-gaming.com/microsoft-cutting-thousands-more-jobs/",
          "source": {
            "name": "Insider Gaming",
            "domain": "insider-gaming.com"
          },
          "metadata": {
            "story_type": "rumour",
            "rumour_status": "rumour",
            "importance": "normal"
          }
        }
      ]
    }
  ]
}
