{
  "id": "2026-03-17",
  "date": "2026-03-17",
  "title": "Game News Round-Up",
  "status": "published",
  "published_at": "2026-03-17T08:56:30.543+00:00",
  "updated_at": null,
  "summary": "Daily curated games-industry news digest for 17 March 2026.",
  "video": {
    "status": "none",
    "url": null,
    "embed_url": null,
    "platform": null,
    "duration_seconds": null
  },
  "sections": [
    {
      "id": "main_news",
      "label": "Game News Round-Up",
      "items": [
        {
          "id": "cyberpunk-2077-ps5-pro-enhanced-update-coming-soon",
          "title": "**Cyberpunk 2077** PS5 Pro enhanced update coming soon",
          "body": null,
          "url": "https://insider-gaming.com/cyberpunk-2077-ps5-pro-enhanced-update-coming-soon/",
          "source": {
            "name": "Insider Gaming",
            "domain": "insider-gaming.com"
          },
          "metadata": {
            "story_type": "confirmed",
            "importance": "normal"
          }
        },
        {
          "id": "nvidia-has-announced-dlss-5-the-next-generation-of-its-image",
          "title": "Nvidia has announced **DLSS 5**, the next generation of its image enhancement technology, which it claims is “the most significant breakthrough in computer graphics since the debut of real-time ray tracing”. Online reaction has been overwhelmingly negative, claiming that the tool creates \"yassified, look-maxxing freaks\"",
          "body": null,
          "url": "https://www.videogameschronicle.com/news/this-is-just-a-garbage-ai-filter-nvidia-met-with-criticism-for-dlss-5s-photoreal-graphics-alterations/",
          "source": {
            "name": "VGC",
            "domain": "videogameschronicle.com"
          },
          "metadata": {
            "story_type": "confirmed",
            "importance": "normal"
          }
        },
        {
          "id": "ps5-pro-s-major-pssr-update-is-rolling-out-to-more-games-thi",
          "title": "PS5 Pro’s major **PSSR** update is rolling out to more games this week including the Silent Hill games, Final Fantasy 7 Rebirth and more",
          "body": null,
          "url": "https://www.videogameschronicle.com/news/ps5-pros-major-pssr-update-is-rolling-out-to-more-games-this-week-with-cyberpunk-2077-to-follow/",
          "source": {
            "name": "VGC",
            "domain": "videogameschronicle.com"
          },
          "metadata": {
            "story_type": "confirmed",
            "importance": "normal"
          }
        },
        {
          "id": "nintendo-released-a-new-handheld-mode-boost-feature-for-swit",
          "title": "**Nintendo** released a new Handheld Mode Boost feature for Switch 2 that makes Switch 1 games use the \"TV mode\" performance modes in Switch 2's handheld mode",
          "body": null,
          "url": "https://www.eurogamer.net/the-nintendo-switch-2-just-got-a-huge-update-that-brings-a-surprise-upgrade-to-loads-of-your-old-switch-games-with-a-few-exceptions",
          "source": {
            "name": "Eurogamer",
            "domain": "eurogamer.net"
          },
          "metadata": {
            "story_type": "confirmed",
            "importance": "normal"
          }
        }
      ]
    },
    {
      "id": "free_games_subscription",
      "label": "Free Games / Subscription",
      "items": []
    },
    {
      "id": "business",
      "label": "Business",
      "items": [
        {
          "id": "court-tells-subnautica-2-publisher-krafton-to-reinstate-fire",
          "title": "Court tells **Subnautica 2** publisher Krafton to reinstate fired CEO and let him handle its Early Access release. Judge ruled that Krafton terminated the game leads' contracts \"without valid cause\"",
          "body": null,
          "url": "https://www.videogameschronicle.com/news/court-tells-subnautica-2-publisher-krafton-to-reinstate-fired-ceo-and-let-him-handle-its-early-access-release/",
          "source": {
            "name": "VGC",
            "domain": "videogameschronicle.com"
          },
          "metadata": {
            "story_type": "confirmed",
            "importance": "normal"
          }
        },
        {
          "id": "saudi-crown-prince-mohammed-bin-salman-s-egdc-firm-has-acqui",
          "title": "Saudi Crown Prince Mohammed Bin Salman’s EGDC firm has acquired 5% of **Capcom** - his public investment fund already bought 5% of the company in 2022",
          "body": null,
          "url": "https://www.videogameschronicle.com/news/saudi-crown-prince-mohammed-bin-salmans-egdc-firm-has-acquired-5-in-capcom/",
          "source": {
            "name": "VGC",
            "domain": "videogameschronicle.com"
          },
          "metadata": {
            "story_type": "confirmed",
            "importance": "normal"
          }
        }
      ]
    },
    {
      "id": "rumours",
      "label": "Rumours",
      "items": []
    }
  ]
}
