{
  "id": "2026-06-05",
  "date": "2026-06-05",
  "title": "Game News Round-Up",
  "status": "published",
  "published_at": "2026-06-05T09:13:15.554+01:00",
  "updated_at": null,
  "summary": "Daily curated games-industry news digest for 5 June 2026.",
  "video": {
    "status": "none",
    "url": null,
    "embed_url": null,
    "platform": null,
    "duration_seconds": null
  },
  "sections": [
    {
      "id": "main_news",
      "label": "Game News Round-Up",
      "items": [
        {
          "id": "nintendo-to-debut-a-switch-2-model-with-replaceable-batterie",
          "title": "Nintendo to debut a **Switch 2** model with replaceable batteries in the EU prior to new EU regulations coming into effect in February 2027",
          "body": null,
          "url": "https://www.gamedeveloper.com/business/nintendo-to-debut-a-switch-2-model-with-replaceable-batteries-in-the-eu",
          "source": {
            "name": "Game Developer",
            "domain": "gamedeveloper.com"
          },
          "metadata": {
            "story_type": "confirmed",
            "importance": "normal"
          }
        },
        {
          "id": "steam-machine-and-steam-frame-confirmed-for-summer-2026-by-v",
          "title": "**Steam Machine** and **Steam Frame** confirmed for summer 2026 by Valve",
          "body": null,
          "url": "https://www.videogameschronicle.com/news/steam-machine-and-steam-frame-confirmed-for-summer-2026-by-valve/",
          "source": {
            "name": "VGC",
            "domain": "videogameschronicle.com"
          },
          "metadata": {
            "story_type": "confirmed",
            "importance": "normal"
          }
        }
      ]
    },
    {
      "id": "free_games_subscription",
      "label": "Free Games / Subscription",
      "items": [
        {
          "id": "xbox-game-pass-games-for-june-have-been-announced-including",
          "title": "**Xbox Game Pass** games for June have been announced, including Herdling, Persona 5 Royal, Frog Sqwad and more",
          "body": null,
          "url": "https://www.eurogamer.net/here-are-our-xbox-game-pass-games-for-june",
          "source": {
            "name": "Eurogamer",
            "domain": "eurogamer.net"
          },
          "metadata": {
            "story_type": "confirmed",
            "importance": "normal"
          }
        }
      ]
    },
    {
      "id": "business",
      "label": "Business",
      "items": [
        {
          "id": "gamble-with-your-friends-sells-two-million-copies-in-a-month",
          "title": "**Gamble With Your Friends** sells two million copies in a month",
          "body": null,
          "url": "https://www.linkedin.com/posts/1-million-copies-sold-in-1-week-2-million-share-7468238891360198656-rbFc/",
          "source": {
            "name": "LinkedIn",
            "domain": "linkedin.com"
          },
          "metadata": {
            "story_type": "confirmed",
            "importance": "normal"
          }
        }
      ]
    },
    {
      "id": "rumours",
      "label": "Rumours",
      "items": []
    },
    {
      "id": "other_notes",
      "label": "Other Notes",
      "items": [
        {
          "id": "please-stay-tuned-tonight-for-a-special-summer-games-fest-ed",
          "title": "Please stay tuned tonight for a special \"Summer Games Fest\" edition of the Game News Round-Up",
          "body": null,
          "url": null,
          "source": null,
          "metadata": {
            "story_type": "note"
          }
        }
      ]
    }
  ]
}
