{
  "id": "2025-05-29",
  "date": "2025-05-29",
  "title": "Game News Round-Up",
  "status": "published",
  "published_at": "2025-05-29T09:28:12.145+01:00",
  "updated_at": null,
  "summary": "Daily curated games-industry news digest for 29 May 2025.",
  "video": {
    "status": "none",
    "url": null,
    "embed_url": null,
    "platform": null,
    "duration_seconds": null
  },
  "sections": [
    {
      "id": "main_news",
      "label": "Game News Round-Up",
      "items": [
        {
          "id": "cyberpunk-2-formally-project-orion-is-now-in-preproduction-c",
          "title": "**Cyberpunk 2** (formally \"Project Orion\") is now in preproduction, CD Projekt says",
          "body": null,
          "url": "https://www.videogameschronicle.com/news/cyberpunk-2-is-now-in-preproduction-cd-projekt-says/",
          "source": {
            "name": "VGC",
            "domain": "videogameschronicle.com"
          },
          "metadata": {
            "story_type": "confirmed",
            "importance": "normal"
          }
        },
        {
          "id": "a-death-stranding-anime-is-in-the-works-hideo-kojima-confirm",
          "title": "A **Death Stranding** anime is in the works, Hideo Kojima confirms",
          "body": null,
          "url": "https://www.videogameschronicle.com/news/a-death-stranding-anime-is-in-the-works-hideo-kojima-confirms/",
          "source": {
            "name": "VGC",
            "domain": "videogameschronicle.com"
          },
          "metadata": {
            "story_type": "confirmed",
            "importance": "normal"
          }
        }
      ]
    },
    {
      "id": "free_games_subscription",
      "label": "Free Games / Subscription",
      "items": []
    },
    {
      "id": "business",
      "label": "Business",
      "items": [
        {
          "id": "ea-has-cancelled-its-black-panther-game-and-closed-its-studi",
          "title": "EA has cancelled its **Black Panther** game and closed its studio **Cliffhanger Games**",
          "body": null,
          "url": "https://www.videogameschronicle.com/news/ea-has-cancelled-its-black-panther-game-and-closed-its-studio-cliffhanger-games/",
          "source": {
            "name": "VGC",
            "domain": "videogameschronicle.com"
          },
          "metadata": {
            "story_type": "confirmed",
            "importance": "normal"
          }
        },
        {
          "id": "amplitude-studios-raises-over-13-million-in-series-a-funding",
          "title": "**Amplitude Studios** raises over $13 million in Series A funding",
          "body": null,
          "url": "https://www.gamesindustry.biz/amplitude-studios-raises-over-13-million-in-series-a-funding",
          "source": {
            "name": "GamesIndustry.biz",
            "domain": "gamesindustry.biz"
          },
          "metadata": {
            "story_type": "confirmed",
            "importance": "normal"
          }
        },
        {
          "id": "cyberpunk-2077-phantom-liberty-has-sold-10-million-copies",
          "title": "**Cyberpunk 2077: Phantom Liberty** Has Sold 10 Million Copies",
          "body": null,
          "url": "https://x.com/CyberpunkGame/status/1927750279316779154",
          "source": {
            "name": "X",
            "domain": "x.com"
          },
          "metadata": {
            "story_type": "confirmed",
            "importance": "normal"
          }
        },
        {
          "id": "the-witcher-3-wild-hunt-has-sold-60-million-copies",
          "title": "The **Witcher 3: Wild Hunt** has sold 60 million copies",
          "body": null,
          "url": "https://x.com/thewitcher/status/1927749997971259697",
          "source": {
            "name": "X",
            "domain": "x.com"
          },
          "metadata": {
            "story_type": "confirmed",
            "importance": "normal"
          }
        }
      ]
    },
    {
      "id": "rumours",
      "label": "Rumours",
      "items": []
    }
  ]
}
