{
  "id": "2024-11-05",
  "date": "2024-11-05",
  "title": "Game News Round-Up",
  "status": "published",
  "published_at": "2024-11-05T09:32:45.11+00:00",
  "updated_at": null,
  "summary": "Daily curated games-industry news digest for 5 November 2024.",
  "video": {
    "status": "none",
    "url": null,
    "embed_url": null,
    "platform": null,
    "duration_seconds": null
  },
  "sections": [
    {
      "id": "main_news",
      "label": "Game News Round-Up",
      "items": []
    },
    {
      "id": "free_games_subscription",
      "label": "Free Games / Subscription",
      "items": [
        {
          "id": "new-xbox-game-pass-titles-for-console-pc-and-cloud-dated",
          "title": "New ** Xbox Game Pass** titles for console, PC and Cloud dated",
          "body": null,
          "url": "https://www.videogameschronicle.com/news/new-xbox-game-pass-titles-for-console-pc-and-cloud-dated-3/",
          "source": {
            "name": "VGC",
            "domain": "videogameschronicle.com"
          },
          "metadata": {
            "story_type": "confirmed",
            "importance": "normal"
          },
          "bullets": [
            "Arriving:",
            "StarCraft: Remastered (PC) – November 5",
            "StarCraft II: Campaign Collection (PC) – November 5",
            "Metal Slug Tactics (Cloud, Console, and PC) – November 5",
            "Go Mecha Ball (Console) – November 6",
            "Harold Halibut (Xbox Series S/X) – November 6",
            "The Rewinder (Console) – November 6",
            "Turnip Boy Robs a Bank (Console) – November 6",
            "Goat Simulator Remastered (Cloud, PC, and Xbox Series S/X) - November 7",
            "Microsoft Flight Simulator 2024 (Cloud, PC, and Xbox Series S/X) - November 19",
            "Leaving (November 15th):",
            "Dicey Dungeons (Cloud, Console, and PC)",
            "Dungeons 4 (Cloud, Console, and PC)",
            "Goat Simulator (PC)",
            "Like a Dragon: Ishin! (Cloud, Console, and PC)",
            "Like a Dragon: The Man Who Erased His Name (Cloud, Console, and PC)",
            "Persona 5 Tactica (Cloud, Console, and PC)",
            "Somerville (Cloud, Console, and PC)"
          ]
        }
      ]
    },
    {
      "id": "business",
      "label": "Business",
      "items": [
        {
          "id": "atari-acquires-transport-tycoon-ip",
          "title": "**Atari** acquires Transport Tycoon IP",
          "body": null,
          "url": "https://www.gamesindustry.biz/atari-acquires-transport-tycoon-ip",
          "source": {
            "name": "GamesIndustry.biz",
            "domain": "gamesindustry.biz"
          },
          "metadata": {
            "story_type": "confirmed",
            "importance": "normal"
          },
          "bullets": [
            "Chris Saywer's classic management game added to publisher's growing portfolio of retro brands",
            "Atari already holds the publishing rights to Chris Sawyer's 2004 spiritual successor Locomotion, as well as sister franchise RollerCoaster Tycoon."
          ]
        },
        {
          "id": "radical-forge-raises-2-6m",
          "title": "**Radical Forge** raises £2.6m",
          "body": null,
          "url": "https://www.gamesindustry.biz/radical-forge-raises-26m",
          "source": {
            "name": "GamesIndustry.biz",
            "domain": "gamesindustry.biz"
          },
          "metadata": {
            "story_type": "confirmed",
            "importance": "normal"
          },
          "bullets": [
            "Investment to go towards team expansion, the release of Southfield, and more",
            "Money raised via NPIF II – Mercia Equity Finance (which is a part of the Northern Powerhouse Investment Fund II)."
          ]
        },
        {
          "id": "supercell-acquires-space-ape",
          "title": "**Supercell** acquires Space Ape",
          "body": null,
          "url": "https://www.gamesindustry.biz/supercell-acquires-space-ape",
          "source": {
            "name": "GamesIndustry.biz",
            "domain": "gamesindustry.biz"
          },
          "metadata": {
            "story_type": "confirmed",
            "importance": "normal"
          },
          "bullets": [
            "The Finnish company already owned 62% of Space Ape, with this acquisition due to close by spring 2025, with a London office operational by then as well."
          ]
        },
        {
          "id": "bethesda-to-shut-down-the-elder-scrolls-legends",
          "title": "**Bethesda** to shut down The Elder Scrolls Legends",
          "body": null,
          "url": "https://www.gamesindustry.biz/bethesda-to-shut-down-the-elder-scrolls-legends",
          "source": {
            "name": "GamesIndustry.biz",
            "domain": "gamesindustry.biz"
          },
          "metadata": {
            "story_type": "confirmed",
            "importance": "normal"
          },
          "bullets": [
            "Servers for card game to be retired in January 2025, has also been delisted on Steam"
          ]
        },
        {
          "id": "remedy-q3-results",
          "title": "**Remedy** Q3 Results",
          "body": null,
          "url": "https://www.gamesindustry.biz/remedy-revenue-rises-129-during-q3-2024",
          "source": {
            "name": "GamesIndustry.biz",
            "domain": "gamesindustry.biz"
          },
          "metadata": {
            "story_type": "confirmed",
            "importance": "normal"
          },
          "bullets": [
            "Revenue: €17.9 million (up 129%)",
            "Operating loss: €2.4 million (compared to operating loss of €5.5 million for same quarter last year)"
          ]
        },
        {
          "id": "nintendo-has-lowered-its-switch-forecast-after-sales-decline",
          "title": "**Nintendo** has lowered its Switch forecast after sales declined 31%",
          "body": null,
          "url": "https://www.videogameschronicle.com/news/nintendo-has-lowered-its-switch-forecast-after-sales-declined-31/",
          "source": {
            "name": "VGC",
            "domain": "videogameschronicle.com"
          },
          "metadata": {
            "story_type": "confirmed",
            "importance": "normal"
          },
          "bullets": [
            "The company made no mention of its next console in its latest earnings report"
          ]
        }
      ]
    },
    {
      "id": "rumours",
      "label": "Rumours",
      "items": [
        {
          "id": "netflix-is-eliminating-its-interactive-shows-in-december",
          "title": "** Netflix** is eliminating its interactive shows in December",
          "body": null,
          "url": "https://www.gamedeveloper.com/business/report-netflix-is-eliminating-its-interactive-shows-in-december",
          "source": {
            "name": "Game Developer",
            "domain": "gamedeveloper.com"
          },
          "metadata": {
            "story_type": "rumour",
            "rumour_status": "rumour",
            "importance": "normal"
          },
          "bullets": [
            "Matt Layzell, creator of the streamer's animated series Battle Kitty, claimed on Instagram that his show and others like it would be removed as Netflix \"wipes the slate clean of their interactive programs.\"",
            "Would include Black Mirror: Bandersnatch and Minecraft: Story Mode",
            "Supposedly happens December 1st"
          ]
        },
        {
          "id": "ubisoft-s-nft-rpg-has-reportedly-been-plagued-by-a-single-pl",
          "title": "**Ubisoft**’s NFT RPG has reportedly been plagued by a single player auto-winning every game",
          "body": null,
          "url": "https://www.videogameschronicle.com/news/ubisofts-nft-rpg-has-reportedly-been-plagued-by-a-single-player-auto-winning-every-game/",
          "source": {
            "name": "VGC",
            "domain": "videogameschronicle.com"
          },
          "metadata": {
            "story_type": "rumour",
            "rumour_status": "rumour",
            "importance": "normal"
          },
          "bullets": [
            "The player has two accounts",
            "Apparently the accounts have been banned but are still auto-winning",
            "As the game is strictly PVP, this renders the game unplayable",
            "Players report they are being automatched with one of the two accounts and auto lose before the match even starts"
          ]
        },
        {
          "id": "pokemon-tcg-pocket-is-currently-earning-3x-more-per-day-than",
          "title": "**Pokemon TCG Pocket** is currently earning 3x more per day than Pokemon Go, estimates suggest",
          "body": null,
          "url": "https://www.videogameschronicle.com/news/pokemon-tcg-pocket-is-currently-earning-3x-more-per-day-than-pokemon-go-estimates-suggest/",
          "source": {
            "name": "VGC",
            "domain": "videogameschronicle.com"
          },
          "metadata": {
            "story_type": "rumour",
            "rumour_status": "rumour",
            "importance": "normal"
          },
          "bullets": [
            "Data suggests the mobile game has made $12 million in the first four days of release"
          ]
        }
      ]
    }
  ]
}
