{
  "id": "2024-05-01",
  "date": "2024-05-01",
  "title": "Game News Round-Up",
  "status": "published",
  "published_at": "2024-05-01T09:57:45.289+01:00",
  "updated_at": null,
  "summary": "Daily curated games-industry news digest for 1 May 2024.",
  "video": {
    "status": "none",
    "url": null,
    "embed_url": null,
    "platform": null,
    "duration_seconds": null
  },
  "sections": [
    {
      "id": "main_news",
      "label": "Game News Round-Up",
      "items": [
        {
          "id": "xbox-games-showcase-and-redacted-direct-announced-for-june-9",
          "title": "**Xbox Games Showcase** and “Redacted” Direct announced for June 9",
          "body": null,
          "url": "https://www.videogameschronicle.com/news/xbox-games-showcase-and-redacted-direct-announced-for-june-9/",
          "source": {
            "name": "VGC",
            "domain": "videogameschronicle.com"
          },
          "metadata": {
            "story_type": "confirmed",
            "importance": "normal"
          },
          "bullets": [
            "June 9, 2024, starting at 10am PT / 1pm ET / 6pm BST",
            "The \"Redacted Direct\" will start immediately after the Xbox Games Showcase",
            {
              "text": "Editors Note: SPOILERS: It's clear \"Redacted\" is the next Call of Duty: Black Ops title.",
              "level": 1
            }
          ]
        },
        {
          "id": "starfield-s-shattered-space-story-expansion-is-launching-thi",
          "title": "**Starfield**’s Shattered Space story expansion is launching this fall",
          "body": null,
          "url": "https://www.videogameschronicle.com/news/starfields-shattered-space-story-expansion-is-launching-this-fall/",
          "source": {
            "name": "VGC",
            "domain": "videogameschronicle.com"
          },
          "metadata": {
            "story_type": "confirmed",
            "importance": "normal"
          },
          "bullets": [
            "Ahead of that, the game's next update will include ship building and city map features",
            "No exact release date atm"
          ]
        }
      ]
    },
    {
      "id": "free_games_subscription",
      "label": "Free Games / Subscription",
      "items": [
        {
          "id": "fallout-4-s-free-next-gen-update-now-available-for-playstati",
          "title": "**Fallout 4**’s free next-gen update now available for PlayStation Plus Collection owners",
          "body": null,
          "url": "https://www.videogameschronicle.com/news/fallout-4s-free-next-gen-update-now-available-for-playstation-plus-collection-owners/",
          "source": {
            "name": "VGC",
            "domain": "videogameschronicle.com"
          },
          "metadata": {
            "story_type": "confirmed",
            "importance": "normal"
          },
          "bullets": [
            "After much confusion and many mixed messages, both PS+ and PS Collection users should now have access to the PS5 update of Fallout 4"
          ]
        },
        {
          "id": "new-xbox-game-pass-titles-for-console-pc-and-cloud-have-been",
          "title": "New **Xbox Game Pass** titles for console, PC and Cloud have been announced",
          "body": null,
          "url": "https://www.videogameschronicle.com/news/new-xbox-game-pass-titles-for-console-pc-and-cloud-have-been-announced-12/",
          "source": {
            "name": "VGC",
            "domain": "videogameschronicle.com"
          },
          "metadata": {
            "story_type": "confirmed",
            "importance": "normal"
          },
          "bullets": [
            "Arriving:",
            "Have A Nice Death (Cloud, Console, and PC) – April 30",
            "Tomb Raider: Definitive Edition (Cloud, Console, and PC) – May 2",
            "Kona II: Brume (Cloud, Console, and PC) – May 7",
            "Little Kitty, Big City (Cloud, Console, and PC) – May 9",
            "Brothers: A Tale of Two Sons (Cloud, Console, and PC) – May 14",
            "Leaving:",
            "May 15th",
            {
              "text": "Eastern Exorcist (Cloud, Console, PC)",
              "level": 2
            },
            {
              "text": "Eiyuden Chronicle Rising (Cloud, Console, PC)",
              "level": 2
            },
            {
              "text": "Fuga: Melodies of Steel 2 (Cloud, Console, PC)",
              "level": 2
            },
            {
              "text": "Ghostlore (Cloud, Console, PC)",
              "level": 2
            },
            {
              "text": "Just Cause 4 Reloaded (Cloud, Console, PC)",
              "level": 2
            },
            {
              "text": "Norco (Cloud, Console, PC)",
              "level": 2
            },
            {
              "text": "SD Gundam Battle Alliance (Cloud, Console, PC)",
              "level": 2
            },
            {
              "text": "Supraland Six Inches Under (Cloud, Console, PC)",
              "level": 2
            }
          ]
        }
      ]
    },
    {
      "id": "business",
      "label": "Business",
      "items": [
        {
          "id": "deliver-us-mars-developer-keoken-interactive-lays-off-team-a",
          "title": "**Deliver Us Mars** developer Keoken Interactive lays off team after failing to find funding at GDC",
          "body": null,
          "url": "https://www.gamesindustry.biz/keoken-interactive-lays-off-team-after-failing-to-find-funding-at-gdc",
          "source": {
            "name": "GamesIndustry.biz",
            "domain": "gamesindustry.biz"
          },
          "metadata": {
            "story_type": "confirmed",
            "importance": "normal"
          },
          "bullets": [
            "13 people affected, only the two co-founders remain",
            "The pair wrote that the team had been let go due to \"nothing substantial materialising directly after our visit to GDC,\" adding: \"We’ve unfortunately exhausted all our possible options for publishing, work for hire, and co-development.\""
          ]
        },
        {
          "id": "hasbro-s-1-billion-bet-on-internal-game-development",
          "title": "**Hasbro**'s $1 billion bet on internal game development",
          "body": null,
          "url": "https://www.gamesindustry.biz/hasbros-1-billion-bet-on-internal-game-development",
          "source": {
            "name": "GamesIndustry.biz",
            "domain": "gamesindustry.biz"
          },
          "metadata": {
            "story_type": "confirmed",
            "importance": "normal"
          },
          "bullets": [
            "Instead of licensing out properties, Hasbro is attempting to build internal teams.",
            "The company has four AAA studios right now:",
            "North Carolina-based Atomic Arcade, which is working on a Snake Eyes GI Joe game",
            "Montreal-based Invoke Studios is working on a Dungeons & Dragons game",
            "Austin, Texas-based Skeleton Key is \"doing something spooky",
            "Another Austin, Texas studio, called Archetype, where BioWare veteran and Star Wars: Knights of the Old Republic lead designer James Ohlen is working on a new franchise called Exodus"
          ]
        },
        {
          "id": "square-enix-abandons-112m-of-in-development-projects-in-an-e",
          "title": "**Square Enix** abandons £112m of in-development projects in an effort to improve quality",
          "body": null,
          "url": "https://www.eurogamer.net/square-enix-abandons-112m-of-in-development-projects-in-an-effort-to-improve-quality",
          "source": {
            "name": "Eurogamer",
            "domain": "eurogamer.net"
          },
          "metadata": {
            "story_type": "confirmed",
            "importance": "normal"
          },
          "bullets": [
            "Will be \"more selective\" moving forward"
          ]
        }
      ]
    },
    {
      "id": "rumours",
      "label": "Rumours",
      "items": []
    }
  ]
}
