{
  "id": "2025-02-17",
  "date": "2025-02-17",
  "title": "Game News Round-Up",
  "status": "published",
  "published_at": "2025-02-17T09:41:54.558+00:00",
  "updated_at": null,
  "summary": "Daily curated games-industry news digest for 17 February 2025.",
  "video": {
    "status": "none",
    "url": null,
    "embed_url": null,
    "platform": null,
    "duration_seconds": null
  },
  "sections": [
    {
      "id": "main_news",
      "label": "Game News Round-Up",
      "items": [
        {
          "id": "n64-cult-classic-platformer-glover-gets-console-release-date",
          "title": "N64 cult classic platformer **Glover** gets console release date",
          "body": null,
          "url": "https://www.eurogamer.net/n64-cult-classic-platformer-glover-gets-console-release-date",
          "source": {
            "name": "Eurogamer",
            "domain": "eurogamer.net"
          },
          "metadata": {
            "story_type": "confirmed",
            "importance": "normal"
          },
          "bullets": [
            "Courtesy of publisher and developer QUByte Interactive, Glover will release across PS4/5, Xbox One/Series S/X, and Nintendo Switch later this month on 27th February.",
            "No visual or gameplay enhancements planned"
          ]
        },
        {
          "id": "influential-dishonored-and-half-life-2-art-lead-viktor-anton",
          "title": "Influential Dishonored and Half-Life 2 art lead **Viktor Antonov** has died",
          "body": null,
          "url": "https://www.videogameschronicle.com/news/influential-dishonored-and-half-life-2-artist-viktor-antonov-has-died/",
          "source": {
            "name": "VGC",
            "domain": "videogameschronicle.com"
          },
          "metadata": {
            "story_type": "confirmed",
            "importance": "normal"
          }
        }
      ]
    },
    {
      "id": "free_games_subscription",
      "label": "Free Games / Subscription",
      "items": []
    },
    {
      "id": "business",
      "label": "Business",
      "items": [
        {
          "id": "embracer-financial-results",
          "title": "**Embracer** Financial Results",
          "body": null,
          "url": "https://www.gamesindustry.biz/embracer-sales-drop-22-to-15bn-298m-debt-remains",
          "source": {
            "name": "GamesIndustry.biz",
            "domain": "gamesindustry.biz"
          },
          "metadata": {
            "story_type": "confirmed",
            "importance": "normal"
          },
          "bullets": [
            "For the three months ending December 31, 2024",
            "Net sales: SEK 7.4 billion ($680 million), down 3% year-on-year, including:",
            "PC/console games: SEK 2.6 billion ($242 million), down 23% year-on-year",
            "Mobile games: SEK 1.6 billion ($149 million), up 2% year-on-year",
            "Net profit: SEK 960 million ($89 million, compared to net loss of SEK 1.8 billion / $167 million during the same period last year)",
            "For the nine months ending December 31, 2024:",
            "Net sales: SEK 16.9 billion ($1.5 billion), down 22% year-on-year including:",
            "PC/console games: SEK 7.3 billion ($679 million), down 35% year-on-year",
            "Mobile games: SEK 4.4 billion ($409 million), down 3% year-on-year",
            "Net loss: SEK 1.3 billion ($121 million, compared to net loss of SEK 1.4 billion / $130 million during the same period last year)"
          ]
        },
        {
          "id": "chinese-video-game-company-papergames-infinity-nikki-love-de",
          "title": "Chinese video game company **Papergames** (Infinity Nikki, Love & Deepspace) generated nearly $1 billion in 2024",
          "body": null,
          "url": "https://www.eurogamer.net/infinity-nikki-studio-papergames-generates-almost-1-billion-in-2024",
          "source": {
            "name": "Eurogamer",
            "domain": "eurogamer.net"
          },
          "metadata": {
            "story_type": "confirmed",
            "importance": "normal"
          },
          "bullets": [
            "Epic Games Store hits 295 million users: <https://www.eurogamer.net/epic-games-store-has-more-pc-players-than-ever-295-million-in-fact>"
          ]
        }
      ]
    },
    {
      "id": "rumours",
      "label": "Rumours",
      "items": [
        {
          "id": "10-10-games-cuts-20-jobs-after-complete-commercial-and-criti",
          "title": "**10:10 Games** cuts 20 jobs after \"complete commercial and critical failure\" of debut game, Funko Fusion",
          "body": null,
          "url": "https://www.eurogamer.net/1010-games-cuts-20-jobs-after-complete-commercial-and-critical-failure-of-debut-game-funko-fusion",
          "source": {
            "name": "Eurogamer",
            "domain": "eurogamer.net"
          },
          "metadata": {
            "story_type": "rumour",
            "rumour_status": "rumour",
            "importance": "normal"
          },
          "bullets": [
            "Sources intimate say no meaningful severance support has been made available, with only \"the bare minimum\" entitlement offered, as well as payment of unused holiday. However, this, some speculate, is why colleagues were pressured into using up all their leave ahead of the announcement.",
            "Some colleagues were apparently notified that their jobs were at risk whilst on leave. In some instances, these staff felt obliged to attend meetings about their future at the studio whilst on holiday, even if they were away in different timezones.",
            "Whilst unconfirmed, it's thought around 20 people have been impacted by the cuts"
          ]
        }
      ]
    }
  ]
}
