{
  "id": "2025-05-09",
  "date": "2025-05-09",
  "title": "Game News Round-Up",
  "status": "published",
  "published_at": "2025-05-09T09:42:03.51+01:00",
  "updated_at": null,
  "summary": "Daily curated games-industry news digest for 9 May 2025.",
  "video": {
    "status": "none",
    "url": null,
    "embed_url": null,
    "platform": null,
    "duration_seconds": null
  },
  "sections": [
    {
      "id": "main_news",
      "label": "Game News Round-Up",
      "items": [
        {
          "id": "gex-trilogy-gets-release-date-ps5-xbox-series-s-x-switch-and",
          "title": "**Gex Trilogy** gets release date (PS5, Xbox Series S/X, Switch and PC on June 16), as well as a $200 collector’s edition with a 3-foot inflatable doll",
          "body": null,
          "url": "https://www.videogameschronicle.com/news/gex-trilogy-gets-release-date-as-well-as-a-200-collectors-edition-with-a-3-foot-inflatable-doll/",
          "source": {
            "name": "VGC",
            "domain": "videogameschronicle.com"
          },
          "metadata": {
            "story_type": "confirmed",
            "importance": "normal"
          }
        },
        {
          "id": "mafia-the-old-country-release-date-august-8-and-50-price-poi",
          "title": "**Mafia: The Old Country** release date (August 8) and $50 price point confirmed",
          "body": null,
          "url": "https://www.videogameschronicle.com/news/mafia-the-old-country-release-date-and-50-price-point-confirmed/",
          "source": {
            "name": "VGC",
            "domain": "videogameschronicle.com"
          },
          "metadata": {
            "story_type": "confirmed",
            "importance": "normal"
          }
        },
        {
          "id": "paradox-announces-europa-universalis-5",
          "title": "Paradox announces **Europa Universalis 5**",
          "body": null,
          "url": "https://www.eurogamer.net/surprising-nobody-paradoxs-long-teased-project-caesar-is-europa-universalis-5",
          "source": {
            "name": "Eurogamer",
            "domain": "eurogamer.net"
          },
          "metadata": {
            "story_type": "confirmed",
            "importance": "normal"
          }
        }
      ]
    },
    {
      "id": "free_games_subscription",
      "label": "Free Games / Subscription",
      "items": []
    },
    {
      "id": "business",
      "label": "Business",
      "items": [
        {
          "id": "tripledot-studios-acquires-applovin-s-mobile-games-business",
          "title": "**Tripledot Studios** acquires AppLovin's mobile games business for $800 million",
          "body": null,
          "url": "https://www.gamesindustry.biz/tripledot-studios-acquires-applovins-mobile-games-business-for-800-million",
          "source": {
            "name": "GamesIndustry.biz",
            "domain": "gamesindustry.biz"
          },
          "metadata": {
            "story_type": "confirmed",
            "importance": "normal"
          },
          "bullets": [
            "The deal means Tripledot will acquire 10 studios, helping it to 'significantly expand its operations' in key markets like the US and Asia.",
            "The deal is half cash and half equity, with AppLovin becoming a minority shareholder of Tripledot Studios. Tripledot expects the deal to close in summer 2025, pending regulator approval."
          ]
        },
        {
          "id": "mobile-studio-fuse-games-receives-7m-investment",
          "title": "Mobile studio **Fuse Games** receives $7m investment",
          "body": null,
          "url": "https://www.gamesindustry.biz/mobile-studio-fuse-games-receives-7m-investment",
          "source": {
            "name": "GamesIndustry.biz",
            "domain": "gamesindustry.biz"
          },
          "metadata": {
            "story_type": "confirmed",
            "importance": "normal"
          }
        },
        {
          "id": "nintendo-financial-results",
          "title": "**Nintendo** Financial Results",
          "body": null,
          "url": "https://www.gamesindustry.biz/nintendo-profits-decline-to-49bn-as-firm-prepares-for-switch-2-launch",
          "source": {
            "name": "GamesIndustry.biz",
            "domain": "gamesindustry.biz"
          },
          "metadata": {
            "story_type": "confirmed",
            "importance": "normal"
          },
          "bullets": [
            "For the full year ended March 31, 2025",
            {
              "text": "Net sales: ¥1.2 trillion ($8.3 billion, down 30.3%)",
              "level": 1
            },
            {
              "text": "Operating profit: ¥282.5 billion ($1.9 billion, down 46.6%)",
              "level": 1
            },
            {
              "text": "Ordinary profit: ¥372.3 billion ($2.5 billion, down 45.3%)",
              "level": 1
            },
            {
              "text": "Gross profit: ¥710.1 billion ($4.9 billion, down 25.5%)",
              "level": 1
            },
            "Forecast for the full year",
            {
              "text": "Net sales: ¥1.9 trillion ($13.1 billion, up 63.1%)",
              "level": 1
            },
            {
              "text": "Operating profit: ¥320 billion ($2.2 billion, up 13.3%)",
              "level": 1
            },
            {
              "text": "Ordinary profit: ¥380 billion ($2.6 billion, up 2.1%)",
              "level": 1
            }
          ]
        }
      ]
    },
    {
      "id": "rumours",
      "label": "Rumours",
      "items": []
    }
  ]
}
