{
  "id": "2026-01-14",
  "date": "2026-01-14",
  "title": "Game News Round-Up",
  "status": "published",
  "published_at": "2026-01-14T09:45:55.331+00:00",
  "updated_at": null,
  "summary": "Daily curated games-industry news digest for 14 January 2026.",
  "video": {
    "status": "none",
    "url": null,
    "embed_url": null,
    "platform": null,
    "duration_seconds": null
  },
  "sections": [
    {
      "id": "main_news",
      "label": "Game News Round-Up",
      "items": [
        {
          "id": "you-don-t-want-to-wrestle-goliath-gog-bosses-say-the-aim-is",
          "title": "‘You don’t want to wrestle Goliath’: **GOG** bosses say the aim is not to defeat Steam, but better it in certain areas - \"Certainly we can do more for classic retro and modern classics\"",
          "body": null,
          "url": "https://www.videogameschronicle.com/news/you-dont-want-to-wrestle-goliath-gog-bosses-say-t[…]-is-not-to-defeat-steam-but-better-it-in-certain-areas/",
          "source": {
            "name": "VGC",
            "domain": "videogameschronicle.com"
          },
          "metadata": {
            "story_type": "confirmed",
            "importance": "normal"
          }
        },
        {
          "id": "judge-denies-request-from-fired-rockstar-employees-to-be-pai",
          "title": "Judge denies request from fired **Rockstar** employees to be paid while legal case is ongoing - the staff failed to show a \"pretty good chance of success\" in proving they were fired for starting a union, the judge said",
          "body": null,
          "url": "https://www.videogameschronicle.com/news/judge-denies-request-from-fired-rockstar-employees-to-be-paid-while-legal-case-is-ongoing/",
          "source": {
            "name": "VGC",
            "domain": "videogameschronicle.com"
          },
          "metadata": {
            "story_type": "confirmed",
            "importance": "normal"
          }
        },
        {
          "id": "rockstar-launches-official-marketplace-for-mods-acquired-fro",
          "title": "**Rockstar** launches official marketplace for mods - Acquired from Cfx (creators of FiveM and RedM). Some mods are free, while bundles can cost several hundred dollars",
          "body": null,
          "url": "https://www.gamesindustry.biz/rockstar-launches-official-marketplace-for-mods",
          "source": {
            "name": "GamesIndustry.biz",
            "domain": "gamesindustry.biz"
          },
          "metadata": {
            "story_type": "confirmed",
            "importance": "normal"
          }
        }
      ]
    },
    {
      "id": "free_games_subscription",
      "label": "Free Games / Subscription",
      "items": []
    },
    {
      "id": "business",
      "label": "Business",
      "items": [
        {
          "id": "meta-has-closed-several-studios-including-splosion-man-studi",
          "title": "**Meta** has closed several studios, including ‘Splosion Man studio Twisted Pixel and Asgard Wrath’s Sanzaru Games",
          "body": null,
          "url": "https://www.videogameschronicle.com/news/meta-has-closed-several-studios-including-splosio[…]n-studio-twisted-pixel-and-asgard-wraths-sanzaru-games/",
          "source": {
            "name": "VGC",
            "domain": "videogameschronicle.com"
          },
          "metadata": {
            "story_type": "confirmed",
            "importance": "normal"
          }
        },
        {
          "id": "ubisoft-hits-the-division-and-avatar-studio-massive-entertai",
          "title": "Ubisoft hits **The Division** and Avatar studio, Massive Entertainment, with layoffs - Around 55 roles could be affected; studio remains focused on future on The Division",
          "body": null,
          "url": "https://www.videogameschronicle.com/news/ubisoft-hits-the-division-and-avatar-studio-massive-entertainment-with-layoffs/",
          "source": {
            "name": "VGC",
            "domain": "videogameschronicle.com"
          },
          "metadata": {
            "story_type": "confirmed",
            "importance": "normal"
          }
        },
        {
          "id": "arc-raiders-has-sold-2-4m-copies-in-2026-so-far",
          "title": "**Arc Raiders** has sold 2.4m copies in 2026 so far",
          "body": null,
          "url": "https://www.gamesindustry.biz/arc-raiders-has-sold-24m-copies-in-2026-so-far",
          "source": {
            "name": "GamesIndustry.biz",
            "domain": "gamesindustry.biz"
          },
          "metadata": {
            "story_type": "confirmed",
            "importance": "normal"
          }
        },
        {
          "id": "larry-major-nelson-has-recently-been-laid-off-by-unity",
          "title": "Larry ‘**Major Nelson**’ has recently been laid off by Unity",
          "body": null,
          "url": "https://bsky.app/profile/hryb.me/post/3mccuyabbv22d",
          "source": {
            "name": "Bluesky",
            "domain": "bsky.app"
          },
          "metadata": {
            "story_type": "confirmed",
            "importance": "normal"
          }
        }
      ]
    },
    {
      "id": "rumours",
      "label": "Rumours",
      "items": []
    }
  ]
}
