{
  "id": "2025-02-03",
  "date": "2025-02-03",
  "title": "Game News Round-Up",
  "status": "published",
  "published_at": "2025-02-03T09:56:32.422+00:00",
  "updated_at": null,
  "summary": "Daily curated games-industry news digest for 3 February 2025.",
  "video": {
    "status": "none",
    "url": null,
    "embed_url": null,
    "platform": null,
    "duration_seconds": null
  },
  "sections": [
    {
      "id": "main_news",
      "label": "Game News Round-Up",
      "items": [
        {
          "id": "pokemon-tcg-pocket-s-trading-feature-is-changing-after-fan-b",
          "title": "**Pokemon TCG Pocket**’s Trading feature is changing after fan backlash",
          "body": null,
          "url": "https://www.videogameschronicle.com/news/pokemon-tcg-pockets-trading-feature-is-changing-after-fan-backlash/",
          "source": {
            "name": "VGC",
            "domain": "videogameschronicle.com"
          },
          "metadata": {
            "story_type": "confirmed",
            "importance": "normal"
          },
          "bullets": [
            "“The item requirements and restrictions implemented for the trading feature were designed to prevent abuse from bots and other prohibited actions using multiple accounts. Our goal was to balance the game while preserving the fun of collecting cards that are core to the Pokemon TCG pocket experience.\"",
            "\"Going forward, we also plan to offer multiple ways to obtain trade tokens including through event distributions.”",
            "Unclear what other changes will be made outside of offering more trade tokens"
          ]
        },
        {
          "id": "the-sims-and-the-sims-2-have-been-officially-re-released-wit",
          "title": "**The Sims** and **The Sims 2** have been officially re-released, with expansions and DLC",
          "body": null,
          "url": "https://www.videogameschronicle.com/news/the-sims-and-the-sims-2-have-been-officially-re-released-with-expansions-included/",
          "source": {
            "name": "VGC",
            "domain": "videogameschronicle.com"
          },
          "metadata": {
            "story_type": "confirmed",
            "importance": "normal"
          },
          "bullets": [
            "All previously released DLC and expansion packs are included, with one exception; IKEA Home Stuff",
            "Both games have been updated to run on Windows 10 and 11, and have an updated rendering engine."
          ]
        },
        {
          "id": "shang-chi-star-simu-liu-says-his-dream-is-a-sleeping-dogs-mo",
          "title": "**Shang-Chi** star Simu Liu says his dream is a Sleeping Dogs movie then a ‘sequel game’",
          "body": null,
          "url": "https://www.videogameschronicle.com/news/shang-chi-star-simu-liu-says-his-dream-is-a-sleeping-dogs-movie-then-a-sequel-game/",
          "source": {
            "name": "VGC",
            "domain": "videogameschronicle.com"
          },
          "metadata": {
            "story_type": "confirmed",
            "importance": "normal"
          },
          "bullets": [
            "The Marvel star says he's \"working with the rights holders\" to make a Sleeping Dogs film happen"
          ]
        }
      ]
    },
    {
      "id": "free_games_subscription",
      "label": "Free Games / Subscription",
      "items": [
        {
          "id": "ridge-racer-64-is-now-on-switch-online-marking-its-first-eve",
          "title": "**Ridge Racer 64** is now on Switch Online, marking its first ever re-release",
          "body": null,
          "url": "https://www.videogameschronicle.com/news/ridge-racer-64-is-now-on-switch-online-marking-its-first-ever-re-release/",
          "source": {
            "name": "VGC",
            "domain": "videogameschronicle.com"
          },
          "metadata": {
            "story_type": "confirmed",
            "importance": "normal"
          }
        }
      ]
    },
    {
      "id": "business",
      "label": "Business",
      "items": [
        {
          "id": "fallout-new-vegas-s-lead-writer-has-re-joined-obsidian-but-i",
          "title": "**Fallout: New Vegas**’s lead writer has re-joined Obsidian, but insists it’s not for a sequel",
          "body": null,
          "url": "https://www.videogameschronicle.com/news/fallout-new-vegass-lead-writer-has-re-joined-obsidian-but-insists-its-not-for-a-sequel/",
          "source": {
            "name": "VGC",
            "domain": "videogameschronicle.com"
          },
          "metadata": {
            "story_type": "confirmed",
            "importance": "normal"
          },
          "bullets": [
            "New Vegas writer John Gonzalez is Obsidian's newest Creative Director"
          ]
        },
        {
          "id": "konami-has-released-its-financial-results-for-the-nine-month",
          "title": "**Konami** has released its financial results for the nine months ending December 31, 2024",
          "body": null,
          "url": "https://www.gamesindustry.biz/konami-revises-forecasts-as-profits-increase-38-to-560m",
          "source": {
            "name": "GamesIndustry.biz",
            "domain": "gamesindustry.biz"
          },
          "metadata": {
            "story_type": "confirmed",
            "importance": "normal"
          },
          "bullets": [
            "Revenue: ¥310.8 billion ($2 billion, up 22.8% year-on-year)",
            "Business profit: ¥87.1 billion ($560 million, up 38.7% year-on-year)",
            "Operating profit: ¥86.7 billion ($557 million, up 45.5% year-on-year)",
            "Digital Entertainment",
            "Revenue: ¥228.8 billion ($1.4 billion, up 32% year-on-year)",
            "Business profit: ¥80.8 billion ($519.7 million, up 44.6% year-on-year)"
          ]
        },
        {
          "id": "multiversus-will-shutdown-on-may-30-after-disappointing-perf",
          "title": "**MultiVersus** will shutdown on May 30 after disappointing performance",
          "body": null,
          "url": "https://www.gamesindustry.biz/multiversus-will-shutdown-on-may-30-after-disappointing-performance",
          "source": {
            "name": "GamesIndustry.biz",
            "domain": "gamesindustry.biz"
          },
          "metadata": {
            "story_type": "confirmed",
            "importance": "normal"
          }
        }
      ]
    },
    {
      "id": "rumours",
      "label": "Rumours",
      "items": []
    }
  ]
}
